france.jpg
sdwl/__init__.py
sdwl/cov_funcs.py
sdwl/expected_periodogram.py
sdwl/grids.py
sdwl/likelihood.py
sdwl/simulation.py
sdwl/spatial_kernel.py
sdwl-0.1.1.dist-info/WHEEL
sdwl-0.1.1.dist-info/METADATA
sdwl-0.1.1.dist-info/RECORD
