Metadata-Version: 2.1
Name: sdwl
Version: 0.1.1
Summary: 
Home-page: http://arthurpgb.pythonanywhere.com/sdw
Keywords: random fields,statistics,whittle,spatial,matern,kriging,interpolation
Author: arthur
Author-email: ahw795@qmul.ac.uk
Requires-Python: >=3.8,<3.11
Classifier: Programming Language :: Python :: 3
Classifier: Programming Language :: Python :: 3.10
Classifier: Programming Language :: Python :: 3.8
Classifier: Programming Language :: Python :: 3.9
Requires-Dist: matplotlib (>=3.1.2,<4.0.0)
Requires-Dist: numpy (>=1.21.5,<2.0.0)
Requires-Dist: scipy (>=1.7.3,<2.0.0)
